profileman/__init__.py
profileman/function.py
profileman-0.0.1.dist-info/METADATA
profileman-0.0.1.dist-info/WHEEL
profileman-0.0.1.dist-info/top_level.txt
profileman-0.0.1.dist-info/RECORD
