Metadata-Version: 2.4
Name: ProfileMan
Version: 0.0.1
Requires-Python: >=3.10
Requires-Dist: numpy
Requires-Dist: matplotlib
